HISTORY.rst
MANIFEST.in
README.rst
setup.py
subler/__init__.py
subler/cli.py
subler/subler.py
subler/tools.py
subler/utils.py
subler.egg-info/PKG-INFO
subler.egg-info/SOURCES.txt
subler.egg-info/dependency_links.txt
subler.egg-info/entry_points.txt
subler.egg-info/not-zip-safe
subler.egg-info/top_level.txt