Metadata-Version: 1.1
Name: subler
Version: 0.4.2
Summary: Python interface to the Subler style metadata tagging.
Home-page: https://github.com/moogar0880/PySubler
Author: Jonathan Nappi
Author-email: moogar@comcast.net
License: UNKNOWN
Platform: UNKNOWN
Classifier: Development Status :: 5 - Production/Stable
Classifier: Intended Audience :: Developers
Classifier: Natural Language :: English
Classifier: Programming Language :: Python
Classifier: Programming Language :: Python :: 2.7
Classifier: Programming Language :: Python :: 3
Classifier: Programming Language :: Python :: 3.4
Classifier: Environment :: MacOS X
Classifier: Operating System :: MacOS :: MacOS X
